{
  "$schema": "https://developer.microsoft.com/json-schemas/fabric/item/report/definition/bookmark/1.4.0/schema.json",
  "displayName": "Reset Filter",
  "name": "4c327d903414590275e6",
  "options": {
    "targetVisualNames": []
  },
  "explorationState": {
    "version": "1.3",
    "activeSection": "7b5e3a8b3af4e356fd96",
    "sections": {
      "7b5e3a8b3af4e356fd96": {
        "visualContainers": {
          "ae9b4bd502491cb3898f": {
            "filters": {
              "byExpr": [
                {
                  "name": "717cc27b2145f65f13e9",
                  "type": "Categorical",
                  "expression": {
                    "Column": {
                      "Expression": {
                        "SourceRef": {
                          "Entity": "2000-2023"
                        }
                      },
                      "Property": "Country / territory"
                    }
                  },
                  "howCreated": 0
                },
                {
                  "name": "1752160be45f24034ed8",
                  "type": "Advanced",
                  "expression": {
                    "Aggregation": {
                      "Expression": {
                        "Column": {
                          "Expression": {
                            "SourceRef": {
                              "Entity": "2000-2023"
                            }
                          },
                          "Property": "GDP Per Capita ($)"
                        }
                      },
                      "Function": 0
                    }
                  },
                  "howCreated": 0
                }
              ]
            },
            "singleVisual": {
              "visualType": "map",
              "objects": {},
              "activeProjections": {
                "Category": [
                  {
                    "Column": {
                      "Expression": {
                        "SourceRef": {
                          "Entity": "2000-2023"
                        }
                      },
                      "Property": "Country / territory"
                    }
                  }
                ]
              }
            }
          },
          "0bc35cff7508cacc3ec3": {
            "filters": {
              "byExpr": [
                {
                  "name": "465490546a4e82b3e90c",
                  "type": "Categorical",
                  "expression": {
                    "Column": {
                      "Expression": {
                        "SourceRef": {
                          "Entity": "2000-2023"
                        }
                      },
                      "Property": "Year"
                    }
                  },
                  "howCreated": 0
                },
                {
                  "name": "046a88d5a7abfd4de7cd",
                  "type": "Advanced",
                  "expression": {
                    "Aggregation": {
                      "Expression": {
                        "Column": {
                          "Expression": {
                            "SourceRef": {
                              "Entity": "2000-2023"
                            }
                          },
                          "Property": "GDP Per Capita ($)"
                        }
                      },
                      "Function": 0
                    }
                  },
                  "howCreated": 0
                },
                {
                  "name": "20c4f843fba17cec33b3",
                  "type": "Categorical",
                  "expression": {
                    "Column": {
                      "Expression": {
                        "SourceRef": {
                          "Entity": "2000-2023"
                        }
                      },
                      "Property": "Country / territory"
                    }
                  },
                  "howCreated": 0
                }
              ]
            },
            "singleVisual": {
              "visualType": "scatterChart",
              "objects": {},
              "activeProjections": {
                "X": [
                  {
                    "Column": {
                      "Expression": {
                        "SourceRef": {
                          "Entity": "2000-2023"
                        }
                      },
                      "Property": "Year"
                    }
                  }
                ]
              }
            }
          },
          "dc3f028b7e55b68e46be": {
            "filters": {
              "byExpr": [
                {
                  "name": "35e1bb6c5c5ec7353eb6",
                  "type": "Categorical",
                  "expression": {
                    "Column": {
                      "Expression": {
                        "SourceRef": {
                          "Entity": "2000-2023"
                        }
                      },
                      "Property": "Country / territory"
                    }
                  },
                  "howCreated": 0
                }
              ]
            },
            "singleVisual": {
              "visualType": "slicer",
              "objects": {
                "merge": {
                  "data": [
                    {
                      "properties": {
                        "mode": {
                          "expr": {
                            "Literal": {
                              "Value": "'Dropdown'"
                            }
                          }
                        }
                      }
                    }
                  ]
                }
              },
              "activeProjections": {
                "Values": [
                  {
                    "Column": {
                      "Expression": {
                        "SourceRef": {
                          "Entity": "2000-2023"
                        }
                      },
                      "Property": "Country / territory"
                    }
                  }
                ]
              }
            }
          },
          "9a49052b5475867dd5d3": {
            "filters": {
              "byExpr": [
                {
                  "name": "350247044b27579b3302",
                  "type": "Categorical",
                  "expression": {
                    "Column": {
                      "Expression": {
                        "SourceRef": {
                          "Entity": "2000-2023"
                        }
                      },
                      "Property": "Year"
                    }
                  },
                  "howCreated": 0
                }
              ]
            },
            "singleVisual": {
              "visualType": "slicer",
              "objects": {
                "merge": {
                  "data": [
                    {
                      "properties": {
                        "mode": {
                          "expr": {
                            "Literal": {
                              "Value": "'Dropdown'"
                            }
                          }
                        }
                      }
                    }
                  ]
                }
              },
              "activeProjections": {
                "Values": [
                  {
                    "Column": {
                      "Expression": {
                        "SourceRef": {
                          "Entity": "2000-2023"
                        }
                      },
                      "Property": "Year"
                    }
                  }
                ]
              }
            }
          }
        }
      }
    },
    "objects": {}
  }
}